<?xml version="1.0" encoding="UTF-8"?>
<launch4jConfig>
  <dontWrapJar>false</dontWrapJar>
  <headerType>console</headerType>
  <jar>F:\Desktop\CodeProjects\java\personal\CookieClickerRPC\target\CookieClickerRPC-1.3.jar</jar>
  <outfile>F:\Desktop\CookieClickerRPC-v1.3-Windows.exe</outfile>
  <errTitle></errTitle>
  <cmdLine></cmdLine>
  <chdir>.</chdir>
  <priority>normal</priority>
  <downloadUrl></downloadUrl>
  <supportUrl></supportUrl>
  <stayAlive>false</stayAlive>
  <restartOnCrash>false</restartOnCrash>
  <manifest></manifest>
  <icon>F:\Desktop\CodeProjects\java\personal\CookieClickerRPC\img\icon.ico</icon>
  <singleInstance>
    <mutexName>Cookie Clicker Rich Presence</mutexName>
    <windowTitle></windowTitle>
  </singleInstance>
  <jre>
    <path>%JAVA_HOME%;%PATH%</path>
    <requiresJdk>false</requiresJdk>
    <requires64Bit>false</requires64Bit>
    <minVersion></minVersion>
    <maxVersion></maxVersion>
  </jre>
</launch4jConfig>